ntfsfind.py
ntfsfind-2.5.0.dist-info/LICENSE
ntfsfind-2.5.0.dist-info/LICENSE.LESSER
ntfsfind-2.5.0.dist-info/METADATA
ntfsfind-2.5.0.dist-info/WHEEL
ntfsfind-2.5.0.dist-info/entry_points.txt
ntfsfind-2.5.0.dist-info/RECORD
