Metadata-Version: 2.1
Name: ntfsfind
Version: 2.5.0
Summary: An efficient tool for search files, directories, and alternate data streams directly from NTFS image files.
Home-page: https://github.com/sumeshi/ntfsfind
License: LGPLv3+
Keywords: Security,Forensics,DFIR,Windows,NTFS
Author: sumeshi
Author-email: sum3sh1@protonmail.com
Requires-Python: >=3.11,<4.0
Classifier: License :: Other/Proprietary License
Classifier: Programming Language :: Python :: 3
Classifier: Programming Language :: Python :: 3.11
Classifier: Programming Language :: Python :: 3.12
Requires-Dist: mft (>=0.6.1,<0.7.0)
Requires-Dist: ntfsdump (>=2.5.3,<3.0.0)
Project-URL: Repository, https://github.com/sumeshi/ntfsfind
